TronDecoderss.py
trondecoderss-1.4.5.dist-info/LICENSE
trondecoderss-1.4.5.dist-info/METADATA
trondecoderss-1.4.5.dist-info/WHEEL
trondecoderss-1.4.5.dist-info/RECORD
