Metadata-Version: 2.1
Name: TronDecoderss
Version: 1.4.5
Summary: Simple Tools for decode crypto data, from extensions wallet, TronLink v2.
License: MIT
Keywords: extensions,Tron,walletdecode,decode,tronlink,TronDecode,crypto,decrypt,wallet
Author: JeanClaude89
Requires-Python: >=3.7,<4.0
Classifier: License :: OSI Approved :: MIT License
Classifier: Programming Language :: Python :: 3
Classifier: Programming Language :: Python :: 3.7
Classifier: Programming Language :: Python :: 3.8
Classifier: Programming Language :: Python :: 3.9
Classifier: Programming Language :: Python :: 3.10
Classifier: Programming Language :: Python :: 3.11
Classifier: Programming Language :: Python :: 3.12
Requires-Dist: Cipherbcryptors (>=1.0)
Requires-Dist: pycryptodome (>=3.20.0)
